limitstates/__init__.py
limitstates/requirements.txt
limitstates/analysis/__init__.py
limitstates/analysis/data.py
limitstates/design/__init__.py
limitstates/design/system.py
limitstates/design/csa/__init__.py
limitstates/design/csa/a23/__init__.py
limitstates/design/csa/a23/c24/Readme.md
limitstates/design/csa/a23/c24/__init__.py
limitstates/design/csa/a23/c24/beamColumn.py
limitstates/design/csa/a23/c24/element.py
limitstates/design/csa/a23/c24/rebarPlacers.py
limitstates/design/csa/a23/c24/section.py
limitstates/design/csa/a23/c24/selection.py
limitstates/design/csa/a23/c24/material/__init__.py
limitstates/design/csa/a23/c24/material/mat.py
limitstates/design/csa/a23/c24/material/_db/clt_prg320_2019.csv
limitstates/design/csa/a23/c24/material/_db/glulam_csa.csv
limitstates/design/csa/o86/__init__.py
limitstates/design/csa/o86/c19/Readme.md
limitstates/design/csa/o86/c19/__init__.py
limitstates/design/csa/o86/c19/annexB.py
limitstates/design/csa/o86/c19/clt.py
limitstates/design/csa/o86/c19/element.py
limitstates/design/csa/o86/c19/fireportection.py
limitstates/design/csa/o86/c19/glulam.py
limitstates/design/csa/o86/c19/section.py
limitstates/design/csa/o86/c19/material/__init__.py
limitstates/design/csa/o86/c19/material/mat.py
limitstates/design/csa/o86/c19/material/_db/clt_prg320_2019.csv
limitstates/design/csa/o86/c19/material/_db/glulam_csa.csv
limitstates/design/csa/s16/__init__.py
limitstates/design/csa/s16/c24/Readme.md
limitstates/design/csa/s16/c24/__init__.py
limitstates/design/csa/s16/c24/beamColumn.py
limitstates/design/csa/s16/c24/connection.py
limitstates/design/csa/s16/c24/element.py
limitstates/design/csa/s16/c24/material.py
limitstates/design/csa/s16/c24/section.py
limitstates/objects/__init__.py
limitstates/objects/display.py
limitstates/objects/fireportection.py
limitstates/objects/geometry.py
limitstates/objects/parse.py
limitstates/objects/read.py
limitstates/objects/relationship.py
limitstates/objects/support.py
limitstates-0.3.1.dist-info/licenses/LICENSE
limitstates-0.3.1.dist-info/METADATA
limitstates-0.3.1.dist-info/WHEEL
limitstates-0.3.1.dist-info/top_level.txt
limitstates-0.3.1.dist-info/RECORD
